<?xml version="1.0" encoding='UTF-8'?>
<ahmidas>
  <params>
    <L> 4 </L>
    <T> 16 </T>
    <!-- position of point source (x,y,z,t) -->
    <position> 0 </position>
    <kappa> 0.10 </kappa>
    <mu> 0.10 </mu>
	<thetax> 0 </thetax>
	<thetay> 0 </thetay>
	<thetaz> 0 </thetaz>
	<thetat> 1 </thetat>
    <APE_steps>  0  </APE_steps>
	<APE_param>  0.5 </APE_param>
	<Jac_steps>  0   </Jac_steps>
    <Jac_param>  4.0 </Jac_param>
    <Fuzz_param> 5 </Fuzz_param>	
	</params>
  <files>
    <!-- u and d quark propagators -->
    <file>
      <type>propagator</type>
      <directory>./prop/</directory>
      <filenameBase>source.</filenameBase>
      <filenameEnding>.inverted</filenameEnding>
      <firstIndex>0</firstIndex>
      <lastIndex>1</lastIndex>
      <indexWidth>2</indexWidth>
    </file>
   <!-- gauge field -->
    <file>
      <type>gauge</type>
      <directory>.</directory>
      <filenameBase>conf.</filenameBase>
      <firstIndex>9999</firstIndex>
      <lastIndex>9999</lastIndex>
      <indexWidth>4</indexWidth>
    </file>
    <file>
      <type>propagator</type>
      <directory>./prop/</directory>
      <filenameBase>source.</filenameBase>
      <firstIndex>0</firstIndex>
      <lastIndex>0</lastIndex>
      <indexWidth>2</indexWidth>
    </file>
  </files>
</ahmidas>
